{
  "todo": [
    {
      "id": 1,
      "title": "Have to complete the assignmnet",
      "status": "completed"
    },
    {
      "id": 2,
      "title": "Have to complete the assignmnet",
      "status": "pending"
    },
    {
      "id": 0.4962499943861225,
      "title": "new assignment",
      "status": "pending"
    },
    {
      "id": 0.33458096119479896,
      "title": "Go to gym",
      "status": "completed"
    },
    {
      "id": 0.585503946495658,
      "title": "complete task 1",
      "status": "todo"
    },
    {
      "id": 0.6188730609355375,
      "title": "complete task 2",
      "status": "completed"
    },
    {
      "id": 0.365559809942851,
      "title": "coplete task3",
      "status": "completed"
    },
    {
      "id": 0.2785413706294382,
      "title": "coplete task4",
      "status": "todo"
    },
    {
      "id": 0.29011384426806686,
      "title": " task 7",
      "status": "completed"
    },
    {
      "id": 0.8685403504265194,
      "title": "task 5",
      "status": "todo"
    },
    {
      "id": 0.12646721170633746,
      "title": "task 8",
      "status": "pending"
    },
    {
      "id": 0.31001027738265097,
      "title": "task9",
      "status": "todo"
    },
    {
      "id": 1.5586826664055287,
      "title": "must complete",
      "status": "pending"
    }
  ],
  "history": []
}